scikit_bloom-0.2.2.dist-info/METADATA
scikit_bloom-0.2.2.dist-info/WHEEL
skbloom.libs/libgcc_s-5b5488a6.so.1
skbloom/utils.py
skbloom/__init__.py
skbloom/skbloom.cpython-311-arm-linux-musleabihf.so
scikit_bloom-0.2.2.dist-info/RECORD
