Metadata-Version: 2.4
Name: scikit-bloom
Version: 0.2.2
Classifier: Programming Language :: Rust
Classifier: Programming Language :: Python :: Implementation :: CPython
Classifier: Programming Language :: Python :: Implementation :: PyPy
Requires-Dist: scikit-learn >=1.5.0
Requires-Dist: scikit-partial >=0.1.0
Requires-Dist: numpy >2
Requires-Python: >=3.10
